{"id": "ANT340H5S20171", "code": "ANT340H5S", "name": "Osteological Theory", "description": "Survey of palaeodemography, palaeopathology, palaeonutrition, and techniques of recovering, preserving and recording human remains. [36L]", "division": "University of Toronto Mississauga", "department": "Anthropology", "prerequisites": "ANT334H5", "exclusions": "ANT334Y5, ANTC48H3", "level": 300, "campus": "UTM", "term": "2017 Winter", "breadths": [], "meeting_sections": [{"code": "L0101", "instructors": ["C Wood"], "times": [{"day": "THURSDAY", "start": 54000, "end": 64800, "duration": 10800, "location": "DH 2080"}], "size": 50, "enrolment": 43}]}