{"id": "CDN335H1S20171", "code": "CDN335H1S", "name": "Black Canadian Studies (formerly UNI335H1)", "description": "An interdisciplinary course that interrogates the constitution of blackness in Canada. Students will study race and ethnic relations, alongside other identity formations such as class, gender and sexuality. Topics to be addressed include media, education, law, immigration and mobility, urbanism, work, political representation and the arts.", "division": "Faculty of Arts and Science", "department": "University College", "prerequisites": "CDN267H1 (formerly UNI267H1), CDN268H1 (formerly UNI268H1)", "exclusions": "UNI335H1", "level": 300, "campus": "UTSG", "term": "2017 Winter", "breadths": [3], "meeting_sections": [{"code": "L0101", "instructors": ["C Thompson"], "times": [{"day": "TUESDAY", "start": 50400, "end": 57600, "duration": 7200, "location": "UC 144"}], "size": 50, "enrolment": 14}]}