{"id": "ENV281H1F20169", "code": "ENV281H1F", "name": "Special Topics in the Environment", "description": "Special topics course designed for students in School of the Environment programs. Content in any given year depends on instructor. \u00a0See School of the Environment website\u00a0for more details.", "division": "Faculty of Arts and Science", "department": "School of Environment", "prerequisites": "Students must have completed a minimum of 4.0 FCEs to register for the course.", "exclusions": "BIG102Y1", "level": 200, "campus": "UTSG", "term": "2016 Fall", "breadths": [3], "meeting_sections": [{"code": "L0101", "instructors": ["S Easterbrook", "M Diamond"], "times": [{"day": "TUESDAY", "start": 50400, "end": 57600, "duration": 7200, "location": "AB 107"}], "size": 60, "enrolment": 40}, {"code": "T0101", "instructors": [], "times": [{"day": "TUESDAY", "start": 57600, "end": 61200, "duration": 3600, "location": "KP 113"}], "size": 30, "enrolment": 27}, {"code": "T0201", "instructors": [], "times": [{"day": "THURSDAY", "start": 57600, "end": 61200, "duration": 3600, "location": "SS 1078"}], "size": 30, "enrolment": 10}]}