{"id": "HMU126H1S20171", "code": "HMU126H1S", "name": "Historical Survey II", "description": "Western music from 1750 to the present.", "division": "Faculty of Music", "department": "Faculty of Music", "prerequisites": "", "exclusions": "", "level": 100, "campus": "UTSG", "term": "2017 Winter", "breadths": [], "meeting_sections": [{"code": "L0101", "instructors": ["E Wright"], "times": [{"day": "MONDAY", "start": 32400, "end": 39600, "duration": 7200, "location": "GI ---"}, {"day": "FRIDAY", "start": 32400, "end": 36000, "duration": 3600, "location": "EJ 109"}, {"day": "FRIDAY", "start": 32400, "end": 36000, "duration": 3600, "location": "EJ 215"}, {"day": "FRIDAY", "start": 32400, "end": 36000, "duration": 3600, "location": "EJ 216"}, {"day": "FRIDAY", "start": 32400, "end": 36000, "duration": 3600, "location": "EJ 217"}, {"day": "FRIDAY", "start": 32400, "end": 36000, "duration": 3600, "location": "EM 108"}, {"day": "FRIDAY", "start": 32400, "end": 36000, "duration": 3600, "location": "EJ 224"}, {"day": "FRIDAY", "start": 32400, "end": 36000, "duration": 3600, "location": "EJ 330"}, {"day": "FRIDAY", "start": 32400, "end": 36000, "duration": 3600, "location": "EJ 130"}], "size": 180, "enrolment": 160}]}