{"id": "JLP374H1F20169", "code": "JLP374H1F", "name": "Psychology of Language ", "description": "Human and other animal communication, structure of human language, word meaning and semantic memory, psychological studies of syntax, bilingualism, language and thought, language errors and disorders.\u00a0 (Sponsored by the Departments of Linguistics and Psychology, but administered solely by the Dept. of Linguistics).", "division": "Faculty of Arts and Science", "department": "Linguistics", "prerequisites": "One FCE from LIN228H1, LIN229H1, LIN232H1, LIN241H1, PSY260H1, PSY270H1, PSY280H1, PSY290H1, COG250Y1", "exclusions": "PSY374H5, PLIC55H3", "level": 300, "campus": "UTSG", "term": "2016 Fall", "breadths": [2], "meeting_sections": [{"code": "L0101", "instructors": ["D Heller"], "times": [{"day": "TUESDAY", "start": 36000, "end": 46800, "duration": 10800, "location": "RS 211"}], "size": 104, "enrolment": 104}]}