{"id": "NMC446H1F20169", "code": "NMC446H1F", "name": "The Babylonian City ", "description": "The course uses written and archaeological evidence to examine the physical form of the Babylonian city in the first millennium BC as the setting for the daily activities of its inhabitants.", "division": "Faculty of Arts and Science", "department": "Near & Middle Eastern Civilizations", "prerequisites": "NMC102H1, NMC346H1/NMC347H1", "exclusions": "", "level": 400, "campus": "UTSG", "term": "2016 Fall", "breadths": [3], "meeting_sections": [{"code": "L0101", "instructors": ["H Baker"], "times": [{"day": "WEDNESDAY", "start": 57600, "end": 68400, "duration": 10800, "location": "BF 214"}], "size": 20, "enrolment": 5}]}