{"id": "NML463H1F20169", "code": "NML463H1F", "name": "Structural Development of Iranian Languages", "description": "This interdisciplinary course focuses on the structural development of Iranian Languages, especially Persian language, from Old Persian (551 BC) to Modern Persian (7th century) with the emphasis on the word formation and grammar. This course examines the role of language in maintaining cultural identity and shows the type and the mechanism of the development of a language in general and of Iranian languages in particular.", "division": "Faculty of Arts and Science", "department": "Near & Middle Eastern Civilizations", "prerequisites": "NML360Y1 or permission of instructor", "exclusions": "", "level": 400, "campus": "UTSG", "term": "2016 Fall", "breadths": [2], "meeting_sections": [{"code": "L0101", "instructors": ["A Hojatollah Taleghani"], "times": [{"day": "TUESDAY", "start": 46800, "end": 54000, "duration": 7200, "location": "SS 1072"}], "size": 30, "enrolment": 8}]}