{"id": "PSY319H5S20171", "code": "PSY319H5S", "name": "Developmental Psychology Laboratory", "description": "Readings, laboratory exercises and research projects designed to familiarize students with methods relevant to research with infants and children. [36P]", "division": "University of Toronto Mississauga", "department": "Psychology", "prerequisites": "PSY(201H5, 202H5)/ equivalent, 210H5/213H5, 309H5", "exclusions": "PSY319H1/PSYC26H3", "level": 300, "campus": "UTM", "term": "2017 Winter", "breadths": [], "meeting_sections": [{"code": "L0101", "instructors": ["G Schellenberg"], "times": [{"day": "THURSDAY", "start": 43200, "end": 54000, "duration": 10800, "location": "DV 1158"}], "size": 20, "enrolment": 16}]}