{"id": "PSYC26H3S20171", "code": "PSYC26H3S", "name": "Developmental Psychology Laboratory", "description": "This course introduces conceptual and practical issues concerning research in developmental psychology. Developmental psychology focuses on the process of change within and across different phases of the life-span. Reflecting the broad range of topics in this area, there are diverse research methods, including techniques for studying infant behaviour as well as procedures for studying development in children, adolescents, and adults. This course will cover a representative sample of some of these approaches.", "division": "University of Toronto Scarborough", "department": "Psychology (UTSC)", "prerequisites": "PSYB01H3 and [PSYB07H3 or (SOCB06H3) or STAB22H3] and PSYB20H3", "exclusions": "PSY319H", "level": 300, "campus": "UTSC", "term": "2017 Winter", "breadths": [], "meeting_sections": [{"code": "L30", "instructors": ["M Schmuckler"], "times": [{"day": "MONDAY", "start": 68400, "end": 75600, "duration": 7200, "location": "SW 316"}], "size": 24, "enrolment": 24}]}