{"id": "RSM321H1F20169", "code": "RSM321H1F", "name": "Advanced Financial Accounting Topics", "description": "This course covers accounting issues and practices relating to long-term investments, consolidations, foreign transactions and foreign investments. International accounting issues are also introduced. Not eligible for CR/NCR option. Contact Rotman Commerce for details.", "division": "Faculty of Arts and Science", "department": "Rotman Commerce", "prerequisites": "RSM320H1", "exclusions": "", "level": 300, "campus": "UTSG", "term": "2016 Fall", "breadths": [5], "meeting_sections": [{"code": "L0101", "instructors": ["J McDonald"], "times": [{"day": "THURSDAY", "start": 50400, "end": 57600, "duration": 7200, "location": "BA 1200"}, {"day": "THURSDAY", "start": 57600, "end": 61200, "duration": 3600, "location": "SS 2102"}], "size": 56, "enrolment": 55}, {"code": "L0201", "instructors": ["G Richardson"], "times": [{"day": "THURSDAY", "start": 57600, "end": 61200, "duration": 3600, "location": "SS 2102"}, {"day": "WEDNESDAY", "start": 50400, "end": 57600, "duration": 7200, "location": "WO 25"}], "size": 51, "enrolment": 49}, {"code": "L0301", "instructors": ["J McDonald"], "times": [{"day": "THURSDAY", "start": 57600, "end": 61200, "duration": 3600, "location": "SS 2102"}, {"day": "WEDNESDAY", "start": 57600, "end": 64800, "duration": 7200, "location": "WO 25"}], "size": 50, "enrolment": 43}]}