{"id": "SOC371H1S20171", "code": "SOC371H1S", "name": "Comparative Political Sociology (formerly SOC270H1)", "description": "The study of comparative (historical and cross-national) variation in outcomes that are the subject of research by political sociologists.", "division": "Faculty of Arts and Science", "department": "Sociology", "prerequisites": "A 200+ level SOC course", "exclusions": "SOC270H1", "level": 300, "campus": "UTSG", "term": "2017 Winter", "breadths": [3], "meeting_sections": [{"code": "L0101", "instructors": ["Y Lee"], "times": [{"day": "WEDNESDAY", "start": 36000, "end": 43200, "duration": 7200, "location": "MS 2170"}], "size": 130, "enrolment": 43}]}