{"id": "TMU418H1F20169", "code": "TMU418H1F", "name": "Styles in Composition", "description": "This directed listening course focuses on understanding historical styles through their compositional processes and distinctive features. Weekly assignments involve listening while following with a score, within a framework provided by the instructor. The repertoire will focus on instrumental and vocal works from the 19th and 20th centuries.", "division": "Faculty of Music", "department": "Faculty of Music", "prerequisites": "TMU220H1, 221H1, 302H1/TMU230H1, 231H1, 232H1", "exclusions": "", "level": 400, "campus": "UTSG", "term": "2016 Fall", "breadths": [], "meeting_sections": [{"code": "L0101", "instructors": ["G Kulesha"], "times": [{"day": "MONDAY", "start": 46800, "end": 54000, "duration": 7200, "location": "EJ 217"}], "size": 20, "enrolment": 13}]}